Metadata-Version: 2.1
Name: pictures
Version: 0.7
Summary: Useful for Image processing
Home-page: https://github.com/stsfaroz/pictures
Author: SALMAN_FAROZ
Author-email: farozsts@gmail.com
License: MIT
Download-URL: https://github.com/stsfaroz/pictures/archive/0.7.tar.gz
Keywords: imagetogif,gif show,images to gif,img2gif
Platform: UNKNOWN
Classifier: Development Status :: 4 - Beta
Classifier: Intended Audience :: Developers
Classifier: Topic :: Software Development :: Build Tools
Classifier: License :: OSI Approved :: MIT License
Classifier: Programming Language :: Python :: 3.6
